apirotater/__init__.py
apirotater/core.py
apirotater-0.5.0.dist-info/licenses/LICENSE
tests/__init__.py
tests/test_apirotater.py
apirotater-0.5.0.dist-info/METADATA
apirotater-0.5.0.dist-info/WHEEL
apirotater-0.5.0.dist-info/top_level.txt
apirotater-0.5.0.dist-info/RECORD
