Metadata-Version: 2.4
Name: apirotater
Version: 0.5.0
Summary: Python library for API key rotation, rate limit control and load balancing
Home-page: https://github.com/mre31/apirotater
Author: mre31
Author-email: y.e.karabag@gmail.com
Project-URL: My Website, https://frondev.com
Keywords: api,api key,api key rotation,rate limit,load balancing
Classifier: Programming Language :: Python :: 3
Classifier: License :: OSI Approved :: MIT License
Classifier: Operating System :: OS Independent
Classifier: Development Status :: 4 - Beta
Classifier: Intended Audience :: Developers
Classifier: Topic :: Software Development :: Libraries :: Python Modules
Requires-Python: >=3.6
License-File: LICENSE
Requires-Dist: python-dotenv>=0.19.0
Dynamic: author
Dynamic: author-email
Dynamic: classifier
Dynamic: description
Dynamic: description-content-type
Dynamic: home-page
Dynamic: keywords
Dynamic: license-file
Dynamic: project-url
Dynamic: requires-dist
Dynamic: requires-python
Dynamic: summary
